literaturescrape/__init__.py
literaturescrape/run.py
literaturescrape/core/__init__.py
literaturescrape/core/models.py
literaturescrape/core/settings.py
literaturescrape/sources/__init__.py
literaturescrape/sources/base.py
literaturescrape/sources/openalex.py
literaturescrape/sources/pubmed.py
literaturescrape/sources/thirdiron.py
test/__init__.py
test/test.py
literaturescrape-0.250205.6.dist-info/LICENSE
literaturescrape-0.250205.6.dist-info/METADATA
literaturescrape-0.250205.6.dist-info/WHEEL
literaturescrape-0.250205.6.dist-info/top_level.txt
literaturescrape-0.250205.6.dist-info/RECORD
