Metadata-Version: 2.1
Name: literaturescrape
Version: 0.250205.6
Summary: Get literature information
Home-page: https://github.com/zzzzls/
Author: zzzzls
Author-email: 245129129@qq.com
License: MIT
Keywords: literature,paper,doi,abstract
License-File: LICENSE
Requires-Dist: curl-cffi >=0.6.2
Requires-Dist: loguru >=0.7.2
